euretikos/__init__.py
euretikos-0.0.1.dist-info/LICENSE
euretikos-0.0.1.dist-info/METADATA
euretikos-0.0.1.dist-info/WHEEL
euretikos-0.0.1.dist-info/top_level.txt
euretikos-0.0.1.dist-info/RECORD
