Metadata-Version: 2.1
Name: euretikos
Version: 0.0.1
Summary: Ingenious Inventor
Author-email: Alexander Fedotov <alex.fedotov@aol.com>
Project-URL: Homepage, https://github.com/euretikos/euretikos
Project-URL: Bug Tracker, https://github.com/euretikos/euretikos/issues
Classifier: Programming Language :: Python :: 3
Classifier: License :: OSI Approved :: MIT License
Classifier: Operating System :: OS Independent
Requires-Python: >=3.10
License-File: LICENSE
